{"1661832900000":["Cocoa Beans","Melon","Nether Wart"],"1661836500000":["Carrot","Potato","Sugar Cane"],"1661840100000":["Cocoa Beans","Mushroom","Wheat"],"1661843700000":["Nether Wart","Potato","Pumpkin"],"1661847300000":["Cactus","Melon","Sugar Cane"],"1661850900000":["Cocoa Beans","Mushroom","Nether Wart"],"1661854500000":["Carrot","Potato","Pumpkin"],"1661858100000":["Melon","Sugar Cane","Wheat"],"1661861700000":["Mushroom","Nether Wart","Sugar Cane"],"1661865300000":["Carrot","Cocoa Beans","Potato"]}